{
  "main": {
    "id": "203c36f663b7c3be",
    "type": "split",
    "children": [
      {
        "id": "ba529799d23c6713",
        "type": "tabs",
        "children": [
          {
            "id": "cc909fa253677d33",
            "type": "leaf",
            "state": {
              "type": "markdown",
              "state": {
                "file": "daliy/2025-11-29.md",
                "mode": "source",
                "source": false
              },
              "icon": "lucide-file",
              "title": "2025-11-29"
            }
          }
        ]
      }
    ],
    "direction": "vertical"
  },
  "left": {
    "id": "c132a506f97d378a",
    "type": "mobile-drawer",
    "children": [
      {
        "id": "b418e9ff9193b007",
        "type": "leaf",
        "state": {
          "type": "file-explorer",
          "state": {
            "sortOrder": "alphabetical",
            "autoReveal": false
          },
          "icon": "lucide-folder-closed",
          "title": "文件列表"
        }
      },
      {
        "id": "ad380ea39f726e6e",
        "type": "leaf",
        "state": {
          "type": "search",
          "state": {
            "query": "",
            "matchingCase": false,
            "explainSearch": false,
            "collapseAll": false,
            "extraContext": false,
            "sortOrder": "alphabetical"
          },
          "icon": "lucide-search",
          "title": "搜索"
        }
      },
      {
        "id": "f3d90a38a22332a4",
        "type": "leaf",
        "state": {
          "type": "tag",
          "state": {
            "sortOrder": "frequency",
            "useHierarchy": true,
            "showSearch": false,
            "searchQuery": ""
          },
          "icon": "lucide-tags",
          "title": "标签"
        }
      },
      {
        "id": "68befd3b9096b4d9",
        "type": "leaf",
        "state": {
          "type": "all-properties",
          "state": {
            "sortOrder": "frequency",
            "showSearch": false,
            "searchQuery": ""
          },
          "icon": "lucide-archive",
          "title": "添加笔记属性"
        }
      },
      {
        "id": "13710dc97aa59291",
        "type": "leaf",
        "state": {
          "type": "bookmarks",
          "state": {},
          "icon": "lucide-bookmark",
          "title": "书签"
        }
      }
    ],
    "currentTab": 0
  },
  "right": {
    "id": "4a74c4e47a30f58b",
    "type": "mobile-drawer",
    "children": [
      {
        "id": "abdd578ab3b53bc8",
        "type": "leaf",
        "state": {
          "type": "backlink",
          "state": {
            "file": "c语言/函数调用.md",
            "collapseAll": false,
            "extraContext": false,
            "sortOrder": "alphabetical",
            "showSearch": false,
            "searchQuery": "",
            "backlinkCollapsed": false,
            "unlinkedCollapsed": true
          },
          "icon": "links-coming-in",
          "title": "反向链接"
        }
      },
      {
        "id": "ee794eaf3e8eb71f",
        "type": "leaf",
        "state": {
          "type": "outgoing-link",
          "state": {
            "linksCollapsed": false,
            "unlinkedCollapsed": true
          },
          "icon": "links-going-out",
          "title": "出链"
        }
      },
      {
        "id": "18af6ef15caef587",
        "type": "leaf",
        "state": {
          "type": "outline",
          "state": {
            "followCursor": false,
            "showSearch": false,
            "searchQuery": ""
          },
          "icon": "lucide-list",
          "title": "大纲"
        }
      }
    ],
    "currentTab": 0
  },
  "left-ribbon": {
    "hiddenItems": {
      "audio-recorder:开始/结束录音": false,
      "workspaces:管理工作区布局": false,
      "switcher:打开快速切换": false,
      "graph:查看关系图谱": false,
      "canvas:新建白板": false,
      "daily-notes:打开/创建今天的日记": false,
      "templates:插入模板": false,
      "command-palette:打开命令面板": false,
      "bases:创建新数据库": false
    }
  },
  "active": "cc909fa253677d33",
  "lastOpenFiles": [
    "c语言/函数调用.md",
    "daliy/2025-11-29.md",
    "c语言/函数.md",
    "c语言/数组.md",
    "c语言/数组与函数.md",
    "c语言/字符串处理函数.md",
    "c语言/字符处理函数.md",
    "daliy/2025-11-25.md",
    "daliy/2025-11-24.md",
    "c语言/概念.md",
    "daliy/2025-11-23.md",
    "daliy/2025-11-21.md",
    "选择排序.md",
    "Pasted image 20251116124539.png",
    "字符串处理函数.md",
    "Pasted image 20251116125009.png",
    "Pasted image 20251115154941.png",
    "Pasted image 20251115154908.png",
    "字符数组.md",
    "字符处理函数.md",
    "Pasted image 20251115155012.png",
    "Pasted image 20251115154817.png",
    "函数.md",
    "markdown.md",
    "Pasted image 20251114152639.png",
    "数组.md",
    "冒泡.md",
    "数组易错.md",
    "Pasted image 20251113201355.png",
    "Pasted image 20251114153209.png",
    "Pasted image 20251114152623.png",
    "未命名.base"
  ]
}